
{"sentences":"玩人丧德，玩物丧志。","source":"《尚书·周书·旅獒》","source_author":"","source_books":"尚书·周书·旅獒"}
{"sentences":"人心惟危，道心惟微，惟精惟一，允执厥中。","source":"《尚书·虞书·大禹谟》","source_author":"","source_books":"尚书·虞书·大禹谟"}
{"sentences":"好问则裕，自用则小","source":"《尚书·商书·仲虺之诰》","source_author":"","source_books":"尚书·商书·仲虺之诰"}
{"sentences":"若升高，必自下，若陟遐，必自迩。","source":"《尚书·商书·太甲下》","source_author":"","source_books":"尚书·商书·太甲下"}
{"sentences":"满招损，谦受益","source":"《尚书·虞书·大禹谟》","source_author":"","source_books":"尚书·虞书·大禹谟"}
{"sentences":"为山九仞，功亏一篑。","source":"《尚书·周书·旅獒》","source_author":"","source_books":"尚书·周书·旅獒"}
{"sentences":"与人不求备，检身若不及","source":"《尚书·商书·伊训》","source_author":"","source_books":"尚书·商书·伊训"}
{"sentences":"惟德动天，无远弗届。满招损，谦受益，时乃天道。","source":"《尚书·虞书·大禹谟》","source_author":"","source_books":"尚书·虞书·大禹谟"}
{"sentences":"民惟邦本，本固邦宁。","source":"《尚书·夏书·五子之歌》","source_author":"","source_books":"尚书·夏书·五子之歌"}
{"sentences":"非知之艰，行之惟艰。","source":"《尚书·商书·说命中》","source_author":"","source_books":"尚书·商书·说命中"}
{"sentences":"宽而栗，柔而立，愿而恭，乱而敬，扰而毅，直而温，简而廉，刚而塞，强而义。","source":"《尚书·虞书·皋陶谟》","source_author":"","source_books":"尚书·虞书·皋陶谟"}
{"sentences":"慎厥身，修思永。","source":"《尚书·虞书·皋陶谟》","source_author":"","source_books":"尚书·虞书·皋陶谟"}
{"sentences":"心之忧危，若蹈虎尾，涉于春冰。","source":"《尚书·周书·君牙》","source_author":"","source_books":"尚书·周书·君牙"}
{"sentences":"诗言志，歌永言，声依永，律和声。","source":"《尚书·虞书·舜典》","source_author":"","source_books":"尚书·虞书·舜典"}
{"sentences":"任贤勿贰，去邪勿疑。","source":"《尚书·虞书·大禹谟》","source_author":"","source_books":"尚书·虞书·大禹谟"}
{"sentences":"罔游于逸，罔淫于乐。","source":"《尚书·虞书·大禹谟》","source_author":"","source_books":"尚书·虞书·大禹谟"}
{"sentences":"木从绳则正，后从谏则圣。","source":"《尚书·商书·说命上》","source_author":"","source_books":"尚书·商书·说命上"}
{"sentences":"树德务滋，除恶务本","source":"《尚书·周书·泰誓》","source_author":"","source_books":"尚书·周书·泰誓"}
{"sentences":"思其艰以图其易","source":"《尚书·周书·君牙》","source_author":"","source_books":"尚书·周书·君牙"}
{"sentences":"知之曰明哲，明哲实作则。","source":"《尚书·商书·说命上》","source_author":"","source_books":"尚书·商书·说命上"}
{"sentences":"君子所，其无逸","source":"《尚书·周书·无逸》","source_author":"","source_books":"尚书·周书·无逸"}
{"sentences":"静言庸违，像恭滔天。","source":"《尚书·虞书·尧典》","source_author":"","source_books":"尚书·虞书·尧典"}
{"sentences":"惟天地万物父母，惟人万物之灵。","source":"《尚书·周书·泰誓》","source_author":"","source_books":"尚书·周书·泰誓"}
{"sentences":"不作无益害有益，功乃成；不贵异物贱用物，民乃足。","source":"《尚书·周书·旅獒》","source_author":"","source_books":"尚书·周书·旅獒"}
{"sentences":"诗言志，歌永言","source":"《尚书·虞书·舜典》","source_author":"","source_books":"尚书·虞书·舜典"}
{"sentences":"建官惟贤，位事惟能。","source":"《尚书·周书·武成》","source_author":"","source_books":"尚书·周书·武成"}
{"sentences":"抚我则后，虐我则仇。","source":"《尚书·周书·泰誓》","source_author":"","source_books":"尚书·周书·泰誓"}
{"sentences":"牝鸡无晨；牝鸡之晨，惟家之索。","source":"《尚书·周书·牧誓》","source_author":"","source_books":"尚书·周书·牧誓"}
{"sentences":"惟德动天，无远弗届。","source":"《尚书·虞书·大禹谟》","source_author":"","source_books":"尚书·虞书·大禹谟"}
{"sentences":"临下以简，御众以宽；罚弗及嗣，赏延于世。","source":"《尚书·虞书·大禹谟》","source_author":"","source_books":"尚书·虞书·大禹谟"}
{"sentences":"稽于众，舍己从人，不虐无告，不废困穷","source":"《尚书·虞书·大禹谟》","source_author":"","source_books":"尚书·虞书·大禹谟"}
{"sentences":"允恭克让，光被四表，格于上下。","source":"《尚书·虞书·尧典》","source_author":"","source_books":"尚书·虞书·尧典"}
{"sentences":"蓄疑败谋，怠忽荒政","source":"《尚书·周书·周官》","source_author":"","source_books":"尚书·周书·周官"}
{"sentences":"人之有能有为，使羞其行，而邦其昌。","source":"《尚书·周书·洪范》","source_author":"","source_books":"尚书·周书·洪范"}
{"sentences":"若农服田力穑，乃亦有秋。","source":"《尚书·商书·盘庚上》","source_author":"","source_books":"尚书·商书·盘庚上"}
{"sentences":"好问则裕，自用则小。","source":"《尚书正义·卷八·仲虺之诰》","source_author":"","source_books":"尚书正义·卷八·仲虺之诰"}
{"sentences":"与国咸休，永世无穷。","source":"《尚书·周书·微子之命》","source_author":"","source_books":"尚书·周书·微子之命"}
{"sentences":"股肱惟人，良臣惟圣。","source":"《尚书·商书·说命下》","source_author":"","source_books":"尚书·商书·说命下"}
{"sentences":"位不期骄，禄不期侈。","source":"《尚书·周书·周官》","source_author":"","source_books":"尚书·周书·周官"}
{"sentences":"必有忍，其乃有济；有容，德乃大。","source":"《尚书·周书·君陈》","source_author":"","source_books":"尚书·周书·君陈"}
{"sentences":"不迩声色，不殖货利。","source":"《尚书·商书·仲虺之诰》","source_author":"","source_books":"尚书·商书·仲虺之诰"}
{"sentences":"慎乃俭德，惟怀永图。","source":"《尚书·商书·太甲上》","source_author":"","source_books":"尚书·商书·太甲上"}
{"sentences":"欲败度，纵败礼","source":"《尚书·商书·太甲中》","source_author":"","source_books":"尚书·商书·太甲中"}
{"sentences":"永敬大恤，无胥绝远！","source":"《尚书·商书·盘庚中》","source_author":"","source_books":"尚书·商书·盘庚中"}
{"sentences":"九族既睦，平章百姓。","source":"《尚书·虞书·尧典》","source_author":"","source_books":"尚书·虞书·尧典"}
{"sentences":"夙夜惟寅，直哉惟清。","source":"《尚书·虞书·舜典》","source_author":"","source_books":"尚书·虞书·舜典"}
{"sentences":"德惟善政，政在养民。","source":"《尚书·虞书·大禹谟》","source_author":"","source_books":"尚书·虞书·大禹谟"}
{"sentences":"予违，汝弼，汝无面从，退有后言。","source":"《尚书·虞书·益稷》","source_author":"","source_books":"尚书·虞书·益稷"}
{"sentences":"民可近，不可下","source":"《尚书·夏书·五子之歌》","source_author":"","source_books":"尚书·夏书·五子之歌"}
{"sentences":"惠迪吉，从逆凶，惟影响。","source":"《尚书·虞书·大禹谟》","source_author":"","source_books":"尚书·虞书·大禹谟"}
{"sentences":"疑谋勿成，百志惟熙。","source":"《尚书·虞书·大禹谟》","source_author":"","source_books":"尚书·虞书·大禹谟"}
{"sentences":"威克厥爱，允济；爱克厥威，允罔功。","source":"《尚书·夏书·胤征》","source_author":"","source_books":"尚书·夏书·胤征"}
{"sentences":"用人惟己，改过不吝。","source":"《尚书·商书·仲虺之诰》","source_author":"","source_books":"尚书·商书·仲虺之诰"}
{"sentences":"克宽克仁，彰信兆民。","source":"《尚书·商书·仲虺之诰》","source_author":"","source_books":"尚书·商书·仲虺之诰"}
{"sentences":"尚克时忱，乃亦有终。","source":"《尚书·商书·汤诰》","source_author":"","source_books":"尚书·商书·汤诰"}
{"sentences":"立爱惟亲，立敬惟长，始于家邦，终于四海。","source":"《尚书·商书·伊训》","source_author":"","source_books":"尚书·商书·伊训"}
{"sentences":"夏德若兹，今朕必往。","source":"《尚书·商书·汤誓》","source_author":"","source_books":"尚书·商书·汤誓"}
{"sentences":"罔违道以干百姓之誉，罔咈百姓以从己之欲。","source":"《尚书·虞书·大禹谟》","source_author":"","source_books":"尚书·虞书·大禹谟"}
{"sentences":"内作色荒，外作禽荒。","source":"《尚书·夏书·五子之歌》","source_author":"","source_books":"尚书·夏书·五子之歌"}
{"sentences":"有典有则，贻厥子孙。","source":"《尚书·夏书·五子之歌》","source_author":"","source_books":"尚书·夏书·五子之歌"}
{"sentences":"弗慎厥德，虽悔可追？","source":"《尚书·夏书·五子之歌》","source_author":"","source_books":"尚书·夏书·五子之歌"}
{"sentences":"臣人克有常宪，百官修辅，厥后惟明明","source":"《尚书·夏书·胤征》","source_author":"","source_books":"尚书·夏书·胤征"}
{"sentences":"敷纳以言，明庶以功，车服以庸。","source":"《尚书·虞书·益稷》","source_author":"","source_books":"尚书·虞书·益稷"}
{"sentences":"箫韶九成，凤皇来仪。","source":"《尚书·虞书·益稷》","source_author":"","source_books":"尚书·虞书·益稷"}
{"sentences":"股肱喜哉！元首起哉！百工熙哉！","source":"《尚书·虞书·益稷》","source_author":"","source_books":"尚书·虞书·益稷"}
{"sentences":"中邦锡土、姓，祗台德先，不距朕行。","source":"《尚书·夏书·禹贡》","source_author":"","source_books":"尚书·夏书·禹贡"}
{"sentences":"大战于甘，乃召六卿。","source":"《尚书·夏书·甘誓》","source_author":"","source_books":"尚书·夏书·甘誓"}
{"sentences":"期于予治，刑期于无刑，民协于中","source":"《尚书·虞书·大禹谟》","source_author":"","source_books":"尚书·虞书·大禹谟"}
{"sentences":"帝德罔愆，临下以简，御众以宽；","source":"《尚书·虞书·大禹谟》","source_author":"","source_books":"尚书·虞书·大禹谟"}
{"sentences":"罚弗及嗣，赏延于世。","source":"《尚书·虞书·大禹谟》","source_author":"","source_books":"尚书·虞书·大禹谟"}
{"sentences":"好生之德，洽于民心","source":"《尚书·虞书·大禹谟》","source_author":"","source_books":"尚书·虞书·大禹谟"}
{"sentences":"无稽之言勿听，弗询之谋勿庸。","source":"《尚书·虞书·大禹谟》","source_author":"","source_books":"尚书·虞书·大禹谟"}
{"sentences":"满招损，谦受益，时乃天道。","source":"《尚书·虞书·大禹谟》","source_author":"","source_books":"尚书·虞书·大禹谟"}
{"sentences":"允迪厥德，谟明弼谐。","source":"《尚书·虞书·皋陶谟》","source_author":"","source_books":"尚书·虞书·皋陶谟"}
{"sentences":"安民则惠，黎民怀之。","source":"《尚书·虞书·皋陶谟》","source_author":"","source_books":"尚书·虞书·皋陶谟"}
{"sentences":"无教逸欲，有邦兢兢业业，一日二日万几。","source":"《尚书·虞书·皋陶谟》","source_author":"","source_books":"尚书·虞书·皋陶谟"}
{"sentences":"天聪明，自我民聪明。","source":"《尚书·虞书·皋陶谟》","source_author":"","source_books":"尚书·虞书·皋陶谟"}
{"sentences":"烝民乃粒，万邦作乂。","source":"《尚书·虞书·益稷》","source_author":"","source_books":"尚书·虞书·益稷"}
{"sentences":"命汝典乐，教胄子，直而温，宽而栗，刚而无虐，简而无傲。","source":"《尚书·虞书·舜典》","source_author":"","source_books":"尚书·虞书·舜典"}
{"sentences":"后克艰厥后，臣克艰厥臣，政乃乂，黎民敏德。","source":"《尚书·虞书·大禹谟》","source_author":"","source_books":"尚书·虞书·大禹谟"}
{"sentences":"野无遗贤，万邦咸宁。","source":"《尚书·虞书·大禹谟》","source_author":"","source_books":"尚书·虞书·大禹谟"}
{"sentences":"百姓昭明，协和万邦。","source":"《尚书·虞书·尧典》","source_author":"","source_books":"尚书·虞书·尧典"}
{"sentences":"乃命羲和，钦若昊天，历象日月星辰，敬授民时。","source":"《尚书·虞书·尧典》","source_author":"","source_books":"尚书·虞书·尧典"}
{"sentences":"慎徽五典，五典克从；","source":"《尚书·虞书·舜典》","source_author":"","source_books":"尚书·虞书·舜典"}
{"sentences":"柔远能迩，惇德允元，而难任人，蛮夷率服。","source":"《尚书·虞书·舜典》","source_author":"","source_books":"尚书·虞书·舜典"}
{"sentences":"克明俊德，以亲九族。","source":"《尚书·虞书·尧典》","source_author":"","source_books":"尚书·虞书·尧典"}
{"sentences":"民罔常怀，怀于有仁。","source":"《尚书·商书·太甲下》","source_author":"","source_books":"尚书·商书·太甲下"}
{"sentences":"一人元良，万邦以贞。","source":"《尚书·商书·太甲下》","source_author":"","source_books":"尚书·商书·太甲下"}
{"sentences":"德懋懋官，功懋懋赏。","source":"《尚书·商书·仲虺之诰》","source_author":"","source_books":"尚书·商书·仲虺之诰"}
{"sentences":"尔身克正，罔敢弗正，民心罔中，惟尔之中。","source":"《尚书·周书·君牙》","source_author":"","source_books":"尚书·周书·君牙"}
{"sentences":"邦之杌陧，曰由一人；邦之荣怀，亦尚一人之庆。","source":"《尚书·周书·秦誓》","source_author":"","source_books":"尚书·周书·秦誓"}
{"sentences":"朝夕纳诲，以辅台德。","source":"《尚书·商书·说命上》","source_author":"","source_books":"尚书·商书·说命上"}
{"sentences":"乃其有备，有备无患。","source":"《尚书·商书·说命中》","source_author":"","source_books":"尚书·商书·说命中"}
{"sentences":"抚民以宽，除其邪虐，功加于时，德垂后裔。","source":"《尚书·周书·微子之命》","source_author":"","source_books":"尚书·周书·微子之命"}
{"sentences":"为善不同，同归于治；为恶不同，同归于乱。","source":"《尚书·周书·蔡仲之命》","source_author":"","source_books":"尚书·周书·蔡仲之命"}
{"sentences":"亦厥君先敬劳，肆徂厥敬劳。","source":"《尚书·周书·梓材》","source_author":"","source_books":"尚书·周书·梓材"}
{"sentences":"奉先思孝，接下思恭。","source":"《尚书·商书·太甲中》","source_author":"","source_books":"尚书·商书·太甲中"}
{"sentences":"式敷民德，永肩一心。","source":"《尚书·商书·盘庚下》","source_author":"","source_books":"尚书·商书·盘庚下"}
